KratosMultiphysics/StructuralMechanicsApplication/__init__.py
KratosMultiphysics/StructuralMechanicsApplication/__init__.pyi
KratosMultiphysics/StructuralMechanicsApplication/adaptative_remeshing_structural_mechanics_analysis.py
KratosMultiphysics/StructuralMechanicsApplication/adaptative_remeshing_structural_mechanics_implicit_dynamic_solver.py
KratosMultiphysics/StructuralMechanicsApplication/adaptative_remeshing_structural_mechanics_static_solver.py
KratosMultiphysics/StructuralMechanicsApplication/adaptative_remeshing_structural_mechanics_utilities.py
KratosMultiphysics/StructuralMechanicsApplication/automatic_rayleigh_parameters_computation_process.py
KratosMultiphysics/StructuralMechanicsApplication/auxiliary_methods_adaptative_solvers.py
KratosMultiphysics/StructuralMechanicsApplication/auxiliary_methods_solvers.py
KratosMultiphysics/StructuralMechanicsApplication/check_eigenvalues_process.py
KratosMultiphysics/StructuralMechanicsApplication/convergence_criteria_factory.py
KratosMultiphysics/StructuralMechanicsApplication/displacement_control_with_direction_process.py
KratosMultiphysics/StructuralMechanicsApplication/distribute_load_on_surface_process.py
KratosMultiphysics/StructuralMechanicsApplication/eigen_solution_input_process.py
KratosMultiphysics/StructuralMechanicsApplication/eigen_solution_output_process.py
KratosMultiphysics/StructuralMechanicsApplication/element_sensitivity_domain_integration_process.py
KratosMultiphysics/StructuralMechanicsApplication/impose_rigid_movement_process.py
KratosMultiphysics/StructuralMechanicsApplication/impose_z_strain_process.py
KratosMultiphysics/StructuralMechanicsApplication/kratos_main_structural.py
KratosMultiphysics/StructuralMechanicsApplication/link_constraint_process.py
KratosMultiphysics/StructuralMechanicsApplication/perturb_geometry_sparse_utility.py
KratosMultiphysics/StructuralMechanicsApplication/perturb_geometry_subgrid_utility.py
kratosstructuralmechanicsapplication-10.4.0.dist-info/METADATA
kratosstructuralmechanicsapplication-10.4.0.dist-info/WHEEL
kratosstructuralmechanicsapplication-10.4.0.dist-info/RECORD
